pypiserver/__init__.py
pypiserver/__main__.py
pypiserver/_app.py
pypiserver/backend.py
pypiserver/bottle.py
pypiserver/cache.py
pypiserver/config.py
pypiserver/core.py
pypiserver/manage.py
pypiserver/pkg_helpers.py
pypiserver/plugin.py
pypiserver/welcome.html
pypiserver_pluggable_backends-1.5.2.dist-info/AUTHORS.rst
pypiserver_pluggable_backends-1.5.2.dist-info/LICENSE.txt
pypiserver_pluggable_backends-1.5.2.dist-info/METADATA
pypiserver_pluggable_backends-1.5.2.dist-info/WHEEL
pypiserver_pluggable_backends-1.5.2.dist-info/entry_points.txt
pypiserver_pluggable_backends-1.5.2.dist-info/top_level.txt
pypiserver_pluggable_backends-1.5.2.dist-info/zip-safe
pypiserver_pluggable_backends-1.5.2.dist-info/RECORD
